{"cik": "0001591596", "entityType": "other", "sic": "", "sicDescription": "", "ownerOrg": null, "insiderTransactionForOwnerExists": 0, "insiderTransactionForIssuerExists": 0, "name": "FIRST TRUST COMBINED SERIES 440", "tickers": [], "exchanges": [], "ein": "000000000", "lei": null, "description": "", "website": "", "investorWebsite": "", "category": "", "fiscalYearEnd": null, "stateOfIncorporation": "", "stateOfIncorporationDescription": "", "addresses": {"mailing": {"street1": "C/O FIRST TRUST PORTFOLIOS L.P.", "street2": "120 EAST LIBERTY DRIVE, SUITE 400", "city": "WHEATON", "stateOrCountry": "IL", "zipCode": "60187", "stateOrCountryDescription": "IL", "isForeignLocation": null, "foreignStateTerritory": null, "country": null, "countryCode": null}, "business": {"street1": "C/O FIRST TRUST PORTFOLIOS L.P.", "street2": "120 EAST LIBERTY DRIVE, SUITE 400", "city": "WHEATON", "stateOrCountry": "IL", "zipCode": "60187", "stateOrCountryDescription": "IL", "isForeignLocation": null, "foreignStateTerritory": null, "country": null, "countryCode": null}}, "phone": "630 765 8000", "flags": "", "formerNames": [], "filings": {"recent": {"accessionNumber": ["0001445546-14-002667", "0001445546-14-001783", "0001445546-14-001609", "0001445546-14-001270"], "filingDate": ["2014-05-27", "2014-03-25", "2014-03-20", "2014-02-26"], "reportDate": ["2014-04-25", "", "", ""], "acceptanceDateTime": ["2014-05-27T09:42:14.000Z", "2014-03-25T14:52:32.000Z", "2014-03-20T15:49:48.000Z", "2014-02-26T13:51:03.000Z"], "act": ["33", "33", "33", "33"], "form": ["24F-2NT", "497J", "487", "S-6"], "fileNumber": ["333-194141", "333-194141", "333-194141", "333-194141"], "filmNumber": ["14868661", "14715690", "14706787", "14643881"], "items": ["", "", "", ""], "core_type": ["24F-2NT", "497J", "487", "S-6"], "size": [4714, 2225, 308373, 200517], "isXBRL": [0, 0, 0, 0], "isInlineXBRL": [0, 0, 0, 0], "primaryDocument": ["CS440.txt", "j497.txt", "s487.txt", "s-6.txt"], "primaryDocDescription": ["05/14 24F-2NT FOR CS440", "DEFINITIVE LETTER", "FORM S-6 TO EFFECTIVE AMENDMENT", "INITIAL REGISTRATION STATEMENT"]}, "files": []}}